lacc/__init__.py
lacc/lab2/__init__.py
lacc/lab2/helpers.py
lacc/lab2/tests/__init__.py
lacc/lab2/tests/helpers.py
lacc/utils/__init__.py
lacc/utils/utils.py
lacc-1.0.2.dist-info/METADATA
lacc-1.0.2.dist-info/WHEEL
lacc-1.0.2.dist-info/top_level.txt
lacc-1.0.2.dist-info/RECORD
