Metadata-Version: 2.1
Name: lacc
Version: 1.0.2
Summary: Find Your Path.
